channelmodel/__init__.py
channelmodel/awgn.py
channelmodel/channel.py
channelmodel/coherence.py
channelmodel/frequencydomainchannel.py
channelmodel/plot_coherence.py
channelmodel/plot_powerdelayprofile.py
channelmodel/powerdelayprofile.py
channelmodel/timevariantchannel.py
py_channelmodel-0.9.3.dist-info/LICENSE
py_channelmodel-0.9.3.dist-info/METADATA
py_channelmodel-0.9.3.dist-info/WHEEL
py_channelmodel-0.9.3.dist-info/entry_points.txt
py_channelmodel-0.9.3.dist-info/top_level.txt
py_channelmodel-0.9.3.dist-info/RECORD
