Metadata-Version: 2.1
Name: py-channelmodel
Version: 0.9.3
Summary: A wireless communication channel model module for simulations.
Author-email: Johannes Demel <demel@ant.uni-bremen.de>
License: GPL-3.0-or-later
Project-URL: Homepage, https://github.com/jdemel/py-channelmodel
Keywords: wireless,simulation,communication,channel,Rayleigh,AWGN
Classifier: License :: OSI Approved :: GNU General Public License v3 or later (GPLv3+)
Classifier: Programming Language :: Python
Classifier: Programming Language :: Python :: 3
Classifier: Intended Audience :: Science/Research
Classifier: Intended Audience :: Telecommunications Industry
Requires-Python: >=3.7
License-File: LICENSE
Requires-Dist: numpy (>=1.17.0)
Requires-Dist: scipy (>=1.3.0)
Provides-Extra: dev
Requires-Dist: black ; extra == 'dev'
Requires-Dist: pytest ; extra == 'dev'
Requires-Dist: bumpver ; extra == 'dev'
Requires-Dist: build ; extra == 'dev'
Requires-Dist: twine ; extra == 'dev'
Provides-Extra: gui
Requires-Dist: matplotlib (>=3.1.0) ; extra == 'gui'
